{"unemployment": "29.8", "area": 199.0, "country": "American Samoa", "median_age_male": "29.9 years", "poverty_line": "NA", "land": "199 sq km", "borders": "none", "languages": "English and Samoan", "region": "Oceania", "capital": "Pago Pago", "population": 57100, "life_expectancy_female": "78.5 years (2016 est.)", "life_expectancy_male": "72.4 years", "water": "0 sq km", "latlng": "-14.33333333, -170.0", "median_age_female": "28.8 years (2016 est.)", "climate": "tropical marine, moderated by southeast trade winds; annual rainfall averages about 3 m; rainy season (November to April), dry season (May to October); little seasonal temperature variation"}