{"country": "Bhutan", "capital": "Thimphu", "population": 1000000.0, "region": "Asia", "area": "38000.0 kilometers squared", "latlng": "27.5, 90.5", "borders": "China and India", "languages": "Dzongkha", "land": 38000.0, "water": 0.0, "climate": "varies; tropical in southern plains; cool winters and hot summers in central valleys; severe winters and cool summers in Himalayas", "median_age_male": "30.0 years", "median_age_female": "30.0 years", "life_expectancy_male": "70.0 years", "life_expectancy_female": "70.0 years", "literacy_male": "70.0%", "literacy_female": "70.0%", "unemployment": "0.0%", "poverty_line": "10.0%"}