{"alpha3Code": ["DMA"], "median_age_male": ["32 years"], "area": ["751 kilometers squared"], "capital": ["Roseau"], "unemployment": ["23%"], "ethnic_groups": ["black", "mixed", "indigenous"], "obesity": ["25%"], "imports": ["manufactured goods", "machinery and equipment", "food", "chemicals"], "population": [71293], "coastline": ["148 kilometers"], "latlng": ["15.41666666, -61.33333333"], "median_age_female": ["33 years"], "climate": ["tropical; moderated by northeast trade winds; heavy rainfall"], "gdp_growth_rate": ["-4%"], "agriculture": ["bananas", "citrus", "mangos", "root crops", "coconuts", "cocoa"], "country": ["Dominica"], "poverty_line": ["29%"], "land": ["751 kilometers squared"], "alpha2Code": ["DM"], "gdp_per_capita": ["$10"], "life_expectancy_male": ["74 years"], "health_expenditures": ["5%"], "region": ["Americas"], "water": ["0 kilometers squared"], "life_expectancy_female": ["80 years"], "natural_resources": ["timber", "hydropower", "arable land"], "languages": ["English"], "pop_growth_rate": ["0%"], "exports": ["bananas", "soap", "bay oil", "vegetables", "grapefruit", "oranges"], "industries": ["soap", "coconut oil", "tourism", "copra", "furniture", "cement blocks", "shoes"]}