{"natural_resources": ["timber", "hydropower", "arable land"], "alpha3Code": ["DMA"], "unemployment": ["23%"], "coastline": ["148 kilometers"], "median_age_female": ["33 years"], "alpha2Code": ["DM"], "languages": ["English"], "region": ["Americas"], "country": ["Dominica"], "pop_growth_rate": ["0%"], "latlng": ["15.41666666, -61.33333333"], "climate": ["tropical; moderated by northeast trade winds; heavy rainfall"], "median_age_male": ["32 years"], "obesity": ["25%"], "poverty_line": ["29%"], "land": ["751 kilometers squared"], "population": [71293], "area": ["751 kilometers squared"], "life_expectancy_female": ["80 years"], "capital": ["Roseau"], "water": ["0 kilometers squared"], "ethnic_groups": ["black", "mixed", "indigenous"], "life_expectancy_male": ["74 years"], "health_expenditures": ["5%"]}