{"country": "Hong Kong", "capital": "City of Victoria", "population": 7000000.0, "region": "Asia", "area": "1000.0 kilometers squared", "latlng": "22.25, 114.16666666", "borders": "China", "languages": "English and Chinese", "land": 1000.0, "water": 0.0, "climate": "subtropical monsoon; cool and humid in winter, hot and rainy from spring through summer, warm and sunny in fall", "median_age_male": "40.0 years", "median_age_female": "40.0 years", "life_expectancy_male": "80.0 years", "life_expectancy_female": "90.0 years", "unemployment": "0.0%", "poverty_line": "20.0%"}