{"natural_resources": ["coal", "mercury", "zinc", "potash", "marble", "barite", "asbestos", "pumice", "fluorspar", "feldspar", "pyrite (sulfur)", "natural gas and crude oil reserves", "fish", "arable land"], "literacy_male": ["99%"], "unemployment": ["11%"], "coastline": ["7600 kilometers"], "education_expenditures": ["4%"], "alpha3Code": ["ITA"], "alpha2Code": ["IT"], "languages": ["Italian"], "region": ["Europe"], "country": ["Italy"], "pop_growth_rate": ["0%"], "latlng": ["42.83333333, 12.83333333"], "climate": ["predominantly Mediterranean; alpine in far north; hot, dry in south"], "median_age_male": ["44 years"], "obesity": ["23%"], "literacy_female": ["99%"], "poverty_line": ["29%"], "land": ["294140 kilometers squared"], "population": [60665551], "health_expenditures": ["9%"], "life_expectancy_female": ["85 years"], "capital": ["Rome"], "water": ["7200 kilometers squared"], "ethnic_groups": ["Italian", "French-"], "life_expectancy_male": ["79 years"], "borders": ["Austria", "France", "San Marino", "Slovenia", "Switzerland", "Holy See"], "median_age_female": ["46 years"], "area": ["301336 kilometers squared"]}