{"alpha3Code": ["SMR"], "median_age_male": ["43 years"], "area": ["61 kilometers squared"], "capital": ["City of San Marino"], "ethnic_groups": ["Sammarinese", "Italian"], "unemployment": ["8%"], "imports": ["wide variety of consumer manufactures", "food", "energy"], "population": [33005], "coastline": ["0 kilometers"], "latlng": ["43.76666666, 12.41666666"], "median_age_female": ["45 years"], "climate": ["Mediterranean; mild to cool winters; warm, sunny summers"], "gdp_growth_rate": ["1%"], "agriculture": ["wheat", "grapes", "corn", "olives; cattle", "pigs", "horses", "beef", "cheese", "hides"], "country": ["San Marino"], "borders": ["Italy"], "land": ["61 kilometers squared"], "alpha2Code": ["SM"], "exports": ["building stone", "lime", "wood", "chestnuts", "wheat", "wine", "baked goods", "hides", "ceramics"], "gdp_per_capita": ["$63"], "life_expectancy_male": ["80 years"], "health_expenditures": ["6%"], "region": ["Europe"], "water": ["0 kilometers squared"], "life_expectancy_female": ["86 years"], "natural_resources": ["building stone"], "languages": ["Italian"], "pop_growth_rate": ["0%"], "education_expenditures": ["2%"], "industries": ["tourism", "banking", "textiles", "electronics", "ceramics", "cement", "wine"]}