{"alpha2Code": ["SX"], "pop_growth_rate": ["1%"], "country": ["Sint Maarten (Dutch part)"], "capital": ["Philipsburg"], "agriculture": ["sugar"], "exports": ["sugar"], "area": ["34 kilometers squared"], "median_age_female": ["41 years"], "climate": ["tropical marine climate, ameliorated by northeast trade winds, results in moderate temperatures; average rainfall of 150 cm/year; hurricane season stretches from July to November"], "coastline": ["58 kilometers"], "population": [38247], "unemployment": ["12%"], "latlng": ["18.033333, -63.05"], "median_age_male": ["39 years"], "gdp_growth_rate": ["3%"], "borders": ["Saint Martin"], "gdp_per_capita": ["$66"], "land": ["34 kilometers squared"], "languages": ["Dutch", "English"], "life_expectancy_female": ["80 years"], "region": ["Americas"], "natural_resources": ["fish", "salt"], "alpha3Code": ["SXM"], "industries": ["tourism", "light industry"], "water": ["0 kilometers squared"], "life_expectancy_male": ["75 years"]}