{"unemployment": "12", "area": 34.0, "country": "Sint Maarten (Dutch part)", "median_age_male": "39.8 years", "land": "34 sq km", "borders": "Saint Martin (French part)", "languages": "Dutch and English", "region": "Americas", "capital": "Philipsburg", "population": 38247, "life_expectancy_female": "80.6 years (2016 est.)", "life_expectancy_male": "75.8 years", "water": "0 sq km", "latlng": "18.033333, -63.05", "median_age_female": "41.7 years (2016 est.)", "climate": "tropical marine climate, ameliorated by northeast trade winds, results in moderate temperatures; average rainfall of 150 cm/year; hurricane season stretches from July to November"}