{"alpha2Code": ["VG"], "pop_growth_rate": ["2%"], "country": ["Virgin Islands (British)"], "capital": ["Road Town"], "agriculture": ["fruits", "vegetables; livestock", "poultry; fish"], "exports": ["rum", "fresh fish", "fruits", "animals; gravel", "sand"], "area": ["151 kilometers squared"], "median_age_female": ["36 years"], "climate": ["subtropical; humid; temperatures moderated by trade winds"], "imports": ["building materials", "automobiles", "foodstuffs", "machinery"], "education_expenditures": ["4%"], "coastline": ["80 kilometers"], "population": [28514], "unemployment": ["8%"], "latlng": ["18.431383, -64.62305"], "median_age_male": ["36 years"], "gdp_growth_rate": ["1%"], "gdp_per_capita": ["$42"], "land": ["151 kilometers squared"], "languages": ["English"], "life_expectancy_female": ["80 years"], "region": ["Americas"], "natural_resources": ["NEGL; pleasant climate", "beaches foster tourism"], "alpha3Code": ["VGB"], "industries": ["tourism", "light industry", "construction", "rum", "concrete block", "offshore banking center"], "water": ["0 kilometers squared"], "life_expectancy_male": ["77 years"], "ethnic_groups": ["African/black", "Latino", "white", "mixed", "Indian", "East"]}