{"country": "Samoa", "capital": "Apia", "population": 0.0, "region": "Oceania", "area": "3000.0 kilometers squared", "latlng": "-13.58333333, -172.33333333", "borders": "none", "languages": "Samoan and English", "land": 3000.0, "water": 0.0, "climate": "tropical; rainy season (November to April), dry season (May to October)", "median_age_male": "20.0 years", "median_age_female": "20.0 years", "life_expectancy_male": "70.0 years", "life_expectancy_female": "80.0 years", "literacy_male": "100.0%", "literacy_female": "100.0%"}