{"life_expectancy_male": "70 years", "climate": "tropical; rainy season (November to April), dry season (May to October)", "life_expectancy_female": "76 years", "water": "10 kilometers squared", "median_age_female": "24 years", "literacy_male": "99%", "population": 194899, "latlng": "-13.58333333, -172.33333333", "median_age_male": "23 years", "languages": "Samoan and English", "country": "Samoa", "region": "Oceania", "land": "2821 kilometers squared", "capital": "Apia", "literacy_female": "99%", "borders": "none", "area": "2842 kilometers squared"}